pytuck/__init__.py
pytuck/py.typed
pytuck/backends/__init__.py
pytuck/backends/backend_binary.py
pytuck/backends/backend_csv.py
pytuck/backends/backend_excel.py
pytuck/backends/backend_json.py
pytuck/backends/backend_sqlite.py
pytuck/backends/backend_xml.py
pytuck/backends/base.py
pytuck/backends/registry.py
pytuck/backends/versions.py
pytuck/common/__init__.py
pytuck/common/crypto.py
pytuck/common/exceptions.py
pytuck/common/options.py
pytuck/common/types.py
pytuck/common/utils.py
pytuck/connectors/__init__.py
pytuck/connectors/base.py
pytuck/connectors/connector_sqlite.py
pytuck/core/__init__.py
pytuck/core/index.py
pytuck/core/orm.py
pytuck/core/session.py
pytuck/core/storage.py
pytuck/core/types.py
pytuck/query/__init__.py
pytuck/query/builder.py
pytuck/query/compiler.py
pytuck/query/result.py
pytuck/query/statements.py
pytuck/tools/__init__.py
pytuck/tools/adapters.py
pytuck/tools/load_external.py
pytuck/tools/migrate.py
pytuck-0.6.2.dist-info/licenses/LICENSE
pytuck-0.6.2.dist-info/METADATA
pytuck-0.6.2.dist-info/WHEEL
pytuck-0.6.2.dist-info/top_level.txt
pytuck-0.6.2.dist-info/RECORD
