Metadata-Version: 2.4
Name: pytuck
Version: 0.6.2
Summary: Lightweight Python document database - No SQL, multi-engine, pluggable persistence
Author: go9sky
Maintainer: go9sky
License-Expression: MIT
Project-URL: Homepage, https://github.com/go9sky/pytuck
Project-URL: Documentation, https://github.com/go9sky/pytuck#readme
Project-URL: Repository, https://github.com/go9sky/pytuck.git
Project-URL: Issues, https://github.com/go9sky/pytuck/issues
Project-URL: Changelog, https://github.com/go9sky/pytuck/blob/master/CHANGELOG.md
Keywords: database,orm,nosql,document-database,python,lightweight,pytuck,embedded-database,key-value-store
Classifier: Development Status :: 3 - Alpha
Classifier: Intended Audience :: Developers
Classifier: Topic :: Database
Classifier: Topic :: Database :: Database Engines/Servers
Classifier: Topic :: Software Development :: Libraries :: Python Modules
Classifier: Operating System :: OS Independent
Classifier: Programming Language :: Python :: 3
Classifier: Programming Language :: Python :: 3.7
Classifier: Programming Language :: Python :: 3.8
Classifier: Programming Language :: Python :: 3.9
Classifier: Programming Language :: Python :: 3.10
Classifier: Programming Language :: Python :: 3.11
Classifier: Programming Language :: Python :: 3.12
Classifier: Programming Language :: Python :: 3.13
Classifier: Typing :: Typed
Requires-Python: >=3.7
License-File: LICENSE
Provides-Extra: json
Provides-Extra: orjson
Requires-Dist: orjson>=3.8.0; extra == "orjson"
Provides-Extra: ujson
Requires-Dist: ujson>=5.5.0; extra == "ujson"
Provides-Extra: csv
Provides-Extra: sqlite
Provides-Extra: excel
Requires-Dist: openpyxl>=3.0.0; extra == "excel"
Provides-Extra: xml
Requires-Dist: lxml>=4.9.0; extra == "xml"
Provides-Extra: all
Requires-Dist: openpyxl>=3.0.0; extra == "all"
Requires-Dist: lxml>=4.9.0; extra == "all"
Requires-Dist: orjson>=3.8.0; extra == "all"
Requires-Dist: ujson>=5.5.0; extra == "all"
Provides-Extra: dev
Requires-Dist: pytest>=7.0.0; extra == "dev"
Requires-Dist: mypy>=0.950; extra == "dev"
Requires-Dist: build>=0.7.0; extra == "dev"
Requires-Dist: twine>=4.0.0; extra == "dev"
Requires-Dist: openpyxl>=3.0.0; extra == "dev"
Requires-Dist: lxml>=4.9.0; extra == "dev"
Requires-Dist: orjson>=3.8.0; extra == "dev"
Requires-Dist: ujson>=5.5.0; extra == "dev"
Dynamic: license-file
